[
  {
    "supplement_name": "Adaptocrine",
    "company": "Apex",
    "units_per_bottle": 90,
    "unit_type": "caps",
    "default_quantity_per_dose": 1,
    "default_frequency_per_day": 3,
    "default_dosage_display": "1 cap 3x/day",
    "cost_per_bottle": 46.98,
    "default_instructions": "With food",
    "refrigerate": false,
    "notes": "",
    "bottles_per_month": 1,
    "active": true,
    "created_at": "2026-02-12T13:23:00.724000",
    "updated_at": "2026-02-12T13:23:00.724000"
  },
  {
    "supplement_name": "Adaptocrine-XL",
    "company": "Apex",
    "units_per_bottle": 120,
    "unit_type": "caps",
    "default_quantity_per_dose": 1,
    "default_frequency_per_day": 3,
    "default_dosage_display": "1 cap 3x/day",
    "cost_per_bottle": 56.98,
    "default_instructions": "With food",
    "refrigerate": false,
    "notes": "",
    "bottles_per_month": null,
    "active": true,
    "created_at": "2026-02-12T13:23:00.724000",
    "updated_at": "2026-02-12T13:23:00.724000"
  },
  {
    "supplement_name": "Advanced Tudca",
    "company": "Cellcore",
    "units_per_bottle": 60,
    "unit_type": "caps",
    "default_quantity_per_dose": 1,
    "default_frequency_per_day": 2,
    "default_dosage_display": "1 cap 2x/day",
    "cost_per_bottle": 89.95,
    "default_instructions": "",
    "refrigerate": false,
    "notes": "",
    "bottles_per_month": 1,
    "active": true,
    "created_at": "2026-02-12T13:23:00.724000",
    "updated_at": "2026-02-12T13:23:00.724000"
  },
  {
    "supplement_name": "AlgaeOmega",
    "company": "Emerson - Nordic Naturals",
    "units_per_bottle": 120,
    "unit_type": "caps",
    "default_quantity_per_dose": 4,
    "default_frequency_per_day": 1,
    "default_dosage_display": "4 caps per day",
    "cost_per_bottle": 53.95,
    "default_instructions": "With food",
    "refrigerate": false,
    "notes": "Algae Omega - For vegetarian patients",
    "bottles_per_month": null,
    "active": true,
    "created_at": "2026-02-12T13:23:00.724000",
    "updated_at": "2026-02-12T13:23:00.724000"
  },
  {
    "supplement_name": "Berberine-X",
    "company": "Biogenetix",
    "units_per_bottle": 60,
    "unit_type": "caps",
    "default_quantity_per_dose": 1,
    "default_frequency_per_day": 1,
    "default_dosage_display": "1 capsule",
    "cost_per_bottle": 65.0,
    "default_instructions": "",
    "refrigerate": false,
    "notes": "1 bottle is a 2 month supply",
    "bottles_per_month": 0.5,
    "active": true,
    "created_at": "2026-02-12T13:23:00.724000",
    "updated_at": "2026-02-12T13:23:00.724000"
  },
  {
    "supplement_name": "Bilemin",
    "company": "Apex",
    "units_per_bottle": 90,
    "unit_type": "caps",
    "default_quantity_per_dose": 2,
    "default_frequency_per_day": 3,
    "default_dosage_display": "2 caps 3x/day",
    "cost_per_bottle": 32.98,
    "default_instructions": "",
    "refrigerate": false,
    "notes": "",
    "bottles_per_month": 2,
    "active": true,
    "created_at": "2026-02-12T13:23:00.724000",
    "updated_at": "2026-02-12T13:23:00.724000"
  },
  {
    "supplement_name": "Biodoph-Fem",
    "company": "Biotics",
    "units_per_bottle": 30,
    "unit_type": "caps",
    "default_quantity_per_dose": 1,
    "default_frequency_per_day": 1,
    "default_dosage_display": "1 cap per day",
    "cost_per_bottle": 35.36,
    "default_instructions": "",
    "refrigerate": false,
    "notes": "",
    "bottles_per_month": 1,
    "active": true,
    "created_at": "2026-02-12T13:23:00.724000",
    "updated_at": "2026-02-12T13:23:00.724000"
  },
  {
    "supplement_name": "Biotoxin Binder",
    "company": "Cellcore",
    "units_per_bottle": 120,
    "unit_type": "caps",
    "default_quantity_per_dose": 2,
    "default_frequency_per_day": 2,
    "default_dosage_display": "2 caps 2x/day",
    "cost_per_bottle": 76.95,
    "default_instructions": "",
    "refrigerate": false,
    "notes": "",
    "bottles_per_month": 1,
    "active": true,
    "created_at": "2026-02-12T13:23:00.724000",
    "updated_at": "2026-02-12T13:23:00.724000"
  },
  {
    "supplement_name": "Bowel Mover",
    "company": "Cellcore",
    "units_per_bottle": 90,
    "unit_type": "caps",
    "default_quantity_per_dose": 2,
    "default_frequency_per_day": 1,
    "default_dosage_display": "1-2 caps at dinner",
    "cost_per_bottle": 51.95,
    "default_instructions": "With dinner",
    "refrigerate": false,
    "notes": "",
    "bottles_per_month": 1,
    "active": true,
    "created_at": "2026-02-12T13:23:00.724000",
    "updated_at": "2026-02-12T13:23:00.724000"
  },
  {
    "supplement_name": "Carboxy",
    "company": "Cell Core",
    "units_per_bottle": 106,
    "unit_type": "scoop",
    "default_quantity_per_dose": 1,
    "default_frequency_per_day": 1,
    "default_dosage_display": "1 scoop per day",
    "cost_per_bottle": 89.95,
    "default_instructions": "",
    "refrigerate": false,
    "notes": "1 bottle is a 3 month supply at 1 scoop per day",
    "bottles_per_month": 0.33,
    "active": true,
    "created_at": "2026-02-12T13:23:00.724000",
    "updated_at": "2026-02-12T13:23:00.724000"
  },
  {
    "supplement_name": "Cholestar-RF",
    "company": "Apex",
    "units_per_bottle": 90,
    "unit_type": "caps",
    "default_quantity_per_dose": 2,
    "default_frequency_per_day": 3,
    "default_dosage_display": "2 caps 3x/day",
    "cost_per_bottle": 43.98,
    "default_instructions": "",
    "refrigerate": false,
    "notes": "",
    "bottles_per_month": 2,
    "active": true,
    "created_at": "2026-02-12T13:23:00.724000",
    "updated_at": "2026-02-12T13:23:00.724000"
  },
  {
    "supplement_name": "Clearvite PSF",
    "company": "Apex",
    "units_per_bottle": 42,
    "unit_type": "serving",
    "default_quantity_per_dose": 1,
    "default_frequency_per_day": 1,
    "default_dosage_display": "Follow program",
    "cost_per_bottle": 77.98,
    "default_instructions": "Follow program",
    "refrigerate": false,
    "notes": "",
    "bottles_per_month": 1,
    "active": true,
    "created_at": "2026-02-12T13:23:00.724000",
    "updated_at": "2026-02-12T13:23:00.724000"
  },
  {
    "supplement_name": "Cortisol Manager",
    "company": "Emerson",
    "units_per_bottle": 90,
    "unit_type": "caps",
    "default_quantity_per_dose": 2,
    "default_frequency_per_day": 1,
    "default_dosage_display": "1-2 per day",
    "cost_per_bottle": 68.5,
    "default_instructions": "",
    "refrigerate": false,
    "notes": "",
    "bottles_per_month": 1,
    "active": true,
    "created_at": "2026-02-12T13:23:00.724000",
    "updated_at": "2026-02-12T13:23:00.724000"
  },
  {
    "supplement_name": "CT Minerals",
    "company": "Cellcore",
    "units_per_bottle": 60,
    "unit_type": "caps",
    "default_quantity_per_dose": 1,
    "default_frequency_per_day": 1,
    "default_dosage_display": "1 cap per day",
    "cost_per_bottle": 56.95,
    "default_instructions": "",
    "refrigerate": false,
    "notes": "1 bottle for 2 months",
    "bottles_per_month": 0.5,
    "active": true,
    "created_at": "2026-02-12T13:23:00.724000",
    "updated_at": "2026-02-12T13:23:00.724000"
  },
  {
    "supplement_name": "CT-Biotic",
    "company": "Cellcore",
    "units_per_bottle": 60,
    "unit_type": "caps",
    "default_quantity_per_dose": 1,
    "default_frequency_per_day": 2,
    "default_dosage_display": "1 cap 2x/day",
    "cost_per_bottle": 56.95,
    "default_instructions": "",
    "refrigerate": false,
    "notes": "",
    "bottles_per_month": 1,
    "active": true,
    "created_at": "2026-02-12T13:23:00.724000",
    "updated_at": "2026-02-12T13:23:00.724000"
  },
  {
    "supplement_name": "DHEA",
    "company": "Apex",
    "units_per_bottle": null,
    "unit_type": "caps",
    "default_quantity_per_dose": null,
    "default_frequency_per_day": null,
    "default_dosage_display": "",
    "cost_per_bottle": 29.98,
    "default_instructions": "",
    "refrigerate": false,
    "notes": "",
    "bottles_per_month": null,
    "active": true,
    "created_at": "2026-02-12T13:23:00.724000",
    "updated_at": "2026-02-12T13:23:00.724000"
  },
  {
    "supplement_name": "DigestZymes",
    "company": "Designs For Health",
    "units_per_bottle": 90,
    "unit_type": "caps",
    "default_quantity_per_dose": 2,
    "default_frequency_per_day": 3,
    "default_dosage_display": "1-2 capsules w/ meals",
    "cost_per_bottle": 40.25,
    "default_instructions": "With meals",
    "refrigerate": false,
    "notes": "",
    "bottles_per_month": null,
    "active": true,
    "created_at": "2026-02-12T13:23:00.724000",
    "updated_at": "2026-02-12T13:23:00.724000"
  },
  {
    "supplement_name": "DIM pro",
    "company": "Pure Encapsulations - Emerson",
    "units_per_bottle": 60,
    "unit_type": "caps",
    "default_quantity_per_dose": 1,
    "default_frequency_per_day": 1,
    "default_dosage_display": "1 cap per day",
    "cost_per_bottle": 62.4,
    "default_instructions": "",
    "refrigerate": false,
    "notes": "1 bottle is a 2 month supply",
    "bottles_per_month": 0.5,
    "active": true,
    "created_at": "2026-02-12T13:23:00.724000",
    "updated_at": "2026-02-12T13:23:00.724000"
  },
  {
    "supplement_name": "Drainage Activator",
    "company": "Cellcore",
    "units_per_bottle": 120,
    "unit_type": "caps",
    "default_quantity_per_dose": 2,
    "default_frequency_per_day": 2,
    "default_dosage_display": "2 caps 2x/day",
    "cost_per_bottle": 59.95,
    "default_instructions": "",
    "refrigerate": false,
    "notes": "",
    "bottles_per_month": 1,
    "active": true,
    "created_at": "2026-02-12T13:23:00.724000",
    "updated_at": "2026-02-12T13:23:00.724000"
  },
  {
    "supplement_name": "Effecsulin",
    "company": "Biogenetix",
    "units_per_bottle": 90,
    "unit_type": "caps",
    "default_quantity_per_dose": 2,
    "default_frequency_per_day": 3,
    "default_dosage_display": "2 caps 3x/day",
    "cost_per_bottle": 50.06,
    "default_instructions": "",
    "refrigerate": false,
    "notes": "",
    "bottles_per_month": 2,
    "active": true,
    "created_at": "2026-02-12T13:23:00.724000",
    "updated_at": "2026-02-12T13:23:00.724000"
  },
  {
    "supplement_name": "GI ResQ",
    "company": "Biogenetix",
    "units_per_bottle": null,
    "unit_type": "caps",
    "default_quantity_per_dose": null,
    "default_frequency_per_day": null,
    "default_dosage_display": "",
    "cost_per_bottle": 109.56,
    "default_instructions": "",
    "refrigerate": false,
    "notes": "",
    "bottles_per_month": null,
    "active": true,
    "created_at": "2026-02-12T13:23:00.724000",
    "updated_at": "2026-02-12T13:23:00.724000"
  },
  {
    "supplement_name": "Glucostatic Balance",
    "company": "Biogenetix",
    "units_per_bottle": 180,
    "unit_type": "caps",
    "default_quantity_per_dose": 2,
    "default_frequency_per_day": 3,
    "default_dosage_display": "2 caps 3x/day",
    "cost_per_bottle": 56.0,
    "default_instructions": "",
    "refrigerate": false,
    "notes": "",
    "bottles_per_month": 1,
    "active": true,
    "created_at": "2026-02-12T13:23:00.724000",
    "updated_at": "2026-02-12T13:23:00.724000"
  },
  {
    "supplement_name": "Glysen-Synergy",
    "company": "Apex",
    "units_per_bottle": 60,
    "unit_type": "packet",
    "default_quantity_per_dose": 2,
    "default_frequency_per_day": 2,
    "default_dosage_display": "2 packets AM / 2 packets PM",
    "cost_per_bottle": 93.98,
    "default_instructions": "",
    "refrigerate": false,
    "notes": "1 container 1 month supply",
    "bottles_per_month": 1,
    "active": true,
    "created_at": "2026-02-12T13:23:00.724000",
    "updated_at": "2026-02-12T13:23:00.724000"
  },
  {
    "supplement_name": "GTA",
    "company": "Biotics",
    "units_per_bottle": 90,
    "unit_type": "caps",
    "default_quantity_per_dose": null,
    "default_frequency_per_day": null,
    "default_dosage_display": "",
    "cost_per_bottle": 28.9,
    "default_instructions": "",
    "refrigerate": false,
    "notes": "",
    "bottles_per_month": null,
    "active": true,
    "created_at": "2026-02-12T13:23:00.724000",
    "updated_at": "2026-02-12T13:23:00.724000"
  },
  {
    "supplement_name": "GTA-Forte",
    "company": "Biotics",
    "units_per_bottle": 90,
    "unit_type": "caps",
    "default_quantity_per_dose": 2,
    "default_frequency_per_day": 1,
    "default_dosage_display": "1-3 caps per day",
    "cost_per_bottle": 46.9,
    "default_instructions": "",
    "refrigerate": false,
    "notes": "For Thyroid",
    "bottles_per_month": null,
    "active": true,
    "created_at": "2026-02-12T13:23:00.724000",
    "updated_at": "2026-02-12T13:23:00.724000"
  },
  {
    "supplement_name": "H-PLR",
    "company": "Apex",
    "units_per_bottle": 90,
    "unit_type": "caps",
    "default_quantity_per_dose": 2,
    "default_frequency_per_day": 3,
    "default_dosage_display": "2-2-2",
    "cost_per_bottle": 47.98,
    "default_instructions": "",
    "refrigerate": false,
    "notes": "",
    "bottles_per_month": 2,
    "active": true,
    "created_at": "2026-02-12T13:23:00.724000",
    "updated_at": "2026-02-12T13:23:00.724000"
  },
  {
    "supplement_name": "HCL-Prozyme",
    "company": "Apex",
    "units_per_bottle": 90,
    "unit_type": "caps",
    "default_quantity_per_dose": 1,
    "default_frequency_per_day": 3,
    "default_dosage_display": "1 before each meal",
    "cost_per_bottle": 36.98,
    "default_instructions": "Before each meal",
    "refrigerate": false,
    "notes": "",
    "bottles_per_month": 1,
    "active": true,
    "created_at": "2026-02-12T13:23:00.724000",
    "updated_at": "2026-02-12T13:23:00.724000"
  },
  {
    "supplement_name": "Hemevite",
    "company": "Apex",
    "units_per_bottle": 90,
    "unit_type": "caps",
    "default_quantity_per_dose": 2,
    "default_frequency_per_day": 3,
    "default_dosage_display": "2-2-2",
    "cost_per_bottle": 31.98,
    "default_instructions": "",
    "refrigerate": false,
    "notes": "Iron Supplement",
    "bottles_per_month": 2,
    "active": true,
    "created_at": "2026-02-12T13:23:00.724000",
    "updated_at": "2026-02-12T13:23:00.724000"
  },
  {
    "supplement_name": "Histaid",
    "company": "Quicksilver Scientific - Emerson",
    "units_per_bottle": 50,
    "unit_type": "pump",
    "default_quantity_per_dose": 2,
    "default_frequency_per_day": 2,
    "default_dosage_display": "2 pumps 2x/day",
    "cost_per_bottle": 49.99,
    "default_instructions": "",
    "refrigerate": false,
    "notes": "",
    "bottles_per_month": 1,
    "active": true,
    "created_at": "2026-02-12T13:23:00.724000",
    "updated_at": "2026-02-12T13:23:00.724000"
  },
  {
    "supplement_name": "HM-ET Binder",
    "company": "Cellcore",
    "units_per_bottle": 120,
    "unit_type": "caps",
    "default_quantity_per_dose": 1,
    "default_frequency_per_day": 2,
    "default_dosage_display": "1 cap 2x/day",
    "cost_per_bottle": 87.95,
    "default_instructions": "",
    "refrigerate": false,
    "notes": "1 bottle for 2 months",
    "bottles_per_month": 0.5,
    "active": true,
    "created_at": "2026-02-12T13:23:00.724000",
    "updated_at": "2026-02-12T13:23:00.724000"
  },
  {
    "supplement_name": "Hypaxx Balance",
    "company": "Biogenetix",
    "units_per_bottle": 90,
    "unit_type": "caps",
    "default_quantity_per_dose": null,
    "default_frequency_per_day": null,
    "default_dosage_display": "",
    "cost_per_bottle": 51.0,
    "default_instructions": "",
    "refrigerate": false,
    "notes": "",
    "bottles_per_month": null,
    "active": true,
    "created_at": "2026-02-12T13:23:00.724000",
    "updated_at": "2026-02-12T13:23:00.724000"
  },
  {
    "supplement_name": "Inflama Control/IFC",
    "company": "Cellcore",
    "units_per_bottle": 120,
    "unit_type": "caps",
    "default_quantity_per_dose": 2,
    "default_frequency_per_day": 2,
    "default_dosage_display": "2 caps 2x/day",
    "cost_per_bottle": 46.95,
    "default_instructions": "",
    "refrigerate": false,
    "notes": "",
    "bottles_per_month": 1,
    "active": true,
    "created_at": "2026-02-12T13:23:00.724000",
    "updated_at": "2026-02-12T13:23:00.724000"
  },
  {
    "supplement_name": "Insomnitol",
    "company": "Designs for Health - Emerson",
    "units_per_bottle": 60,
    "unit_type": "caps",
    "default_quantity_per_dose": 2,
    "default_frequency_per_day": 1,
    "default_dosage_display": "1-2 caps before bed",
    "cost_per_bottle": 50.25,
    "default_instructions": "Before bed",
    "refrigerate": false,
    "notes": "",
    "bottles_per_month": 1,
    "active": true,
    "created_at": "2026-02-12T13:23:00.724000",
    "updated_at": "2026-02-12T13:23:00.724000"
  },
  {
    "supplement_name": "KL Support",
    "company": "Cellcore",
    "units_per_bottle": 120,
    "unit_type": "caps",
    "default_quantity_per_dose": 2,
    "default_frequency_per_day": 2,
    "default_dosage_display": "2 caps 2x/day",
    "cost_per_bottle": 61.95,
    "default_instructions": "",
    "refrigerate": false,
    "notes": "",
    "bottles_per_month": 1,
    "active": true,
    "created_at": "2026-02-12T13:23:00.724000",
    "updated_at": "2026-02-12T13:23:00.724000"
  },
  {
    "supplement_name": "Liposomal Glutathione",
    "company": "Quicksilver Scientific - Emerson",
    "units_per_bottle": 50,
    "unit_type": "pump",
    "default_quantity_per_dose": 2,
    "default_frequency_per_day": 2,
    "default_dosage_display": "2 pumps 2x/day",
    "cost_per_bottle": 50.99,
    "default_instructions": "",
    "refrigerate": true,
    "notes": "",
    "bottles_per_month": 1,
    "active": true,
    "created_at": "2026-02-12T13:23:00.724000",
    "updated_at": "2026-02-12T13:23:00.724000"
  },
  {
    "supplement_name": "Liposomal Glutathione (Pills)",
    "company": "Pure Encapsulations - Emerson",
    "units_per_bottle": 60,
    "unit_type": "caps",
    "default_quantity_per_dose": 2,
    "default_frequency_per_day": 1,
    "default_dosage_display": "2 pills per day",
    "cost_per_bottle": 110.0,
    "default_instructions": "",
    "refrigerate": false,
    "notes": "There are big pills just FYI",
    "bottles_per_month": 1,
    "active": true,
    "created_at": "2026-02-12T13:23:00.724000",
    "updated_at": "2026-02-12T13:23:00.724000"
  },
  {
    "supplement_name": "Liposomal Methyl B-12",
    "company": "Quicksilver Scientific - Emerson",
    "units_per_bottle": 30,
    "unit_type": "pump",
    "default_quantity_per_dose": 2,
    "default_frequency_per_day": 1,
    "default_dosage_display": "2 pumps",
    "cost_per_bottle": 53.0,
    "default_instructions": "",
    "refrigerate": false,
    "notes": "",
    "bottles_per_month": 1,
    "active": true,
    "created_at": "2026-02-12T13:23:00.724000",
    "updated_at": "2026-02-12T13:23:00.724000"
  },
  {
    "supplement_name": "Liposomal Methyl B-Complex + Lemon Raspberry",
    "company": "Quicksilver Scientific - Emerson",
    "units_per_bottle": 50,
    "unit_type": "pump",
    "default_quantity_per_dose": 2,
    "default_frequency_per_day": 1,
    "default_dosage_display": "2 pumps",
    "cost_per_bottle": 50.99,
    "default_instructions": "",
    "refrigerate": false,
    "notes": "",
    "bottles_per_month": 1,
    "active": true,
    "created_at": "2026-02-12T13:23:00.724000",
    "updated_at": "2026-02-12T13:23:00.724000"
  },
  {
    "supplement_name": "Liposomal Vitamin C with R-Lipoic Acid",
    "company": "Quicksilver - Emerson",
    "units_per_bottle": 50,
    "unit_type": "pump",
    "default_quantity_per_dose": 2,
    "default_frequency_per_day": 2,
    "default_dosage_display": "2 pumps, 2x per day",
    "cost_per_bottle": 33.99,
    "default_instructions": "",
    "refrigerate": true,
    "notes": "",
    "bottles_per_month": 1,
    "active": true,
    "created_at": "2026-02-12T13:23:00.724000",
    "updated_at": "2026-02-12T13:23:00.724000"
  },
  {
    "supplement_name": "LymphActive",
    "company": "Cellcore",
    "units_per_bottle": 60,
    "unit_type": "caps",
    "default_quantity_per_dose": 1,
    "default_frequency_per_day": 2,
    "default_dosage_display": "1 cap 2x/day",
    "cost_per_bottle": 51.95,
    "default_instructions": "",
    "refrigerate": false,
    "notes": "",
    "bottles_per_month": 1,
    "active": true,
    "created_at": "2026-02-12T13:23:00.724000",
    "updated_at": "2026-02-12T13:23:00.724000"
  },
  {
    "supplement_name": "Metaboclear (Chocolate)",
    "company": "Biogenetix",
    "units_per_bottle": null,
    "unit_type": "serving",
    "default_quantity_per_dose": null,
    "default_frequency_per_day": null,
    "default_dosage_display": "",
    "cost_per_bottle": 80.25,
    "default_instructions": "",
    "refrigerate": false,
    "notes": "",
    "bottles_per_month": null,
    "active": true,
    "created_at": "2026-02-12T13:23:00.724000",
    "updated_at": "2026-02-12T13:23:00.724000"
  },
  {
    "supplement_name": "Metaboclear (Vanilla)",
    "company": "Biogenetix",
    "units_per_bottle": null,
    "unit_type": "serving",
    "default_quantity_per_dose": null,
    "default_frequency_per_day": null,
    "default_dosage_display": "",
    "cost_per_bottle": 80.25,
    "default_instructions": "",
    "refrigerate": false,
    "notes": "",
    "bottles_per_month": null,
    "active": true,
    "created_at": "2026-02-12T13:23:00.724000",
    "updated_at": "2026-02-12T13:23:00.724000"
  },
  {
    "supplement_name": "Metacrin-DX",
    "company": "Apex",
    "units_per_bottle": 90,
    "unit_type": "caps",
    "default_quantity_per_dose": 2,
    "default_frequency_per_day": 3,
    "default_dosage_display": "2 caps 3x/day",
    "cost_per_bottle": 39.98,
    "default_instructions": "",
    "refrigerate": false,
    "notes": "",
    "bottles_per_month": 2,
    "active": true,
    "created_at": "2026-02-12T13:23:00.724000",
    "updated_at": "2026-02-12T13:23:00.724000"
  },
  {
    "supplement_name": "Methyl-SP",
    "company": "Apex",
    "units_per_bottle": 90,
    "unit_type": "caps",
    "default_quantity_per_dose": 2,
    "default_frequency_per_day": 3,
    "default_dosage_display": "2 caps 3x/day",
    "cost_per_bottle": 39.98,
    "default_instructions": "",
    "refrigerate": false,
    "notes": "",
    "bottles_per_month": 2,
    "active": true,
    "created_at": "2026-02-12T13:23:00.724000",
    "updated_at": "2026-02-12T13:23:00.724000"
  },
  {
    "supplement_name": "Motility PRO",
    "company": "Ortho Molecular - Emerson",
    "units_per_bottle": 60,
    "unit_type": "caps",
    "default_quantity_per_dose": 1,
    "default_frequency_per_day": 1,
    "default_dosage_display": "1 per day",
    "cost_per_bottle": 43.3,
    "default_instructions": "",
    "refrigerate": false,
    "notes": "Good substitute for bowel mover. 1 bottle is a 2 month supply",
    "bottles_per_month": 0.5,
    "active": true,
    "created_at": "2026-02-12T13:23:00.724000",
    "updated_at": "2026-02-12T13:23:00.724000"
  },
  {
    "supplement_name": "NAD+Gold",
    "company": "Quicksilver - Emerson",
    "units_per_bottle": 50,
    "unit_type": "pump",
    "default_quantity_per_dose": 2,
    "default_frequency_per_day": 2,
    "default_dosage_display": "2 pumps, 2x per day",
    "cost_per_bottle": 68.99,
    "default_instructions": "",
    "refrigerate": true,
    "notes": "",
    "bottles_per_month": 1,
    "active": true,
    "created_at": "2026-02-12T13:23:00.724000",
    "updated_at": "2026-02-12T13:23:00.724000"
  },
  {
    "supplement_name": "Nanoemulsified CoQ10",
    "company": "Quicksilver Scientific - Emerson",
    "units_per_bottle": 50,
    "unit_type": "pump",
    "default_quantity_per_dose": 2,
    "default_frequency_per_day": 2,
    "default_dosage_display": "2 pumps 2x/day",
    "cost_per_bottle": 55.99,
    "default_instructions": "",
    "refrigerate": true,
    "notes": "",
    "bottles_per_month": 1,
    "active": true,
    "created_at": "2026-02-12T13:23:00.724000",
    "updated_at": "2026-02-12T13:23:00.724000"
  },
  {
    "supplement_name": "Nanoemulsified Vitamin D3-K2",
    "company": "Quicksilver - Emerson",
    "units_per_bottle": 50,
    "unit_type": "pump",
    "default_quantity_per_dose": 3,
    "default_frequency_per_day": 1,
    "default_dosage_display": "3 pumps",
    "cost_per_bottle": 55.99,
    "default_instructions": "",
    "refrigerate": false,
    "notes": "",
    "bottles_per_month": 1,
    "active": true,
    "created_at": "2026-02-12T13:23:00.724000",
    "updated_at": "2026-02-12T13:23:00.724000"
  },
  {
    "supplement_name": "Neo-40",
    "company": "Human - Emerson",
    "units_per_bottle": 60,
    "unit_type": "caps",
    "default_quantity_per_dose": 1,
    "default_frequency_per_day": 2,
    "default_dosage_display": "1AM and 1PM for 30 days. Then 1 per day.",
    "cost_per_bottle": 74.95,
    "default_instructions": "",
    "refrigerate": false,
    "notes": "1 bottle first 30 days- 1 bottle is 2 month supply after",
    "bottles_per_month": 1,
    "active": true,
    "created_at": "2026-02-12T13:23:00.724000",
    "updated_at": "2026-02-12T13:23:00.724000"
  },
  {
    "supplement_name": "Omegagenics EPA-DHA 720 Lemon",
    "company": "Metagenics - Emerson",
    "units_per_bottle": 120,
    "unit_type": "caps",
    "default_quantity_per_dose": 2,
    "default_frequency_per_day": 1,
    "default_dosage_display": "2 caps",
    "cost_per_bottle": 58.75,
    "default_instructions": "",
    "refrigerate": true,
    "notes": "",
    "bottles_per_month": 0.5,
    "active": true,
    "created_at": "2026-02-12T13:23:00.724000",
    "updated_at": "2026-02-12T13:23:00.724000"
  },
  {
    "supplement_name": "OmegaGenics EPA-DHA 2400 (Liquid Omega)",
    "company": "Emerson - Metagenics",
    "units_per_bottle": 150,
    "unit_type": "ml",
    "default_quantity_per_dose": 2,
    "default_frequency_per_day": 1,
    "default_dosage_display": "2 teaspoon per day",
    "cost_per_bottle": 57.5,
    "default_instructions": "",
    "refrigerate": true,
    "notes": "Liquid Omega",
    "bottles_per_month": 1,
    "active": true,
    "created_at": "2026-02-12T13:23:00.724000",
    "updated_at": "2026-02-12T13:23:00.724000"
  },
  {
    "supplement_name": "Para 1",
    "company": "Cellcore",
    "units_per_bottle": 120,
    "unit_type": "caps",
    "default_quantity_per_dose": 2,
    "default_frequency_per_day": 2,
    "default_dosage_display": "2 caps 2x/day",
    "cost_per_bottle": 46.98,
    "default_instructions": "",
    "refrigerate": false,
    "notes": "",
    "bottles_per_month": 1,
    "active": true,
    "created_at": "2026-02-12T13:23:00.724000",
    "updated_at": "2026-02-12T13:23:00.724000"
  },
  {
    "supplement_name": "Para 2",
    "company": "Cellcore",
    "units_per_bottle": 120,
    "unit_type": "caps",
    "default_quantity_per_dose": 2,
    "default_frequency_per_day": 2,
    "default_dosage_display": "2 caps 2x/day",
    "cost_per_bottle": 53.98,
    "default_instructions": "",
    "refrigerate": false,
    "notes": "",
    "bottles_per_month": 1,
    "active": true,
    "created_at": "2026-02-12T13:23:00.724000",
    "updated_at": "2026-02-12T13:23:00.724000"
  },
  {
    "supplement_name": "Para 4",
    "company": "Cellcore",
    "units_per_bottle": 120,
    "unit_type": "caps",
    "default_quantity_per_dose": 2,
    "default_frequency_per_day": 2,
    "default_dosage_display": "2 caps 2x/day",
    "cost_per_bottle": 62.95,
    "default_instructions": "",
    "refrigerate": false,
    "notes": "",
    "bottles_per_month": 1,
    "active": true,
    "created_at": "2026-02-12T13:23:00.724000",
    "updated_at": "2026-02-12T13:23:00.724000"
  },
  {
    "supplement_name": "Pregnenolone",
    "company": "Apex",
    "units_per_bottle": null,
    "unit_type": "caps",
    "default_quantity_per_dose": null,
    "default_frequency_per_day": null,
    "default_dosage_display": "",
    "cost_per_bottle": 29.98,
    "default_instructions": "",
    "refrigerate": false,
    "notes": "",
    "bottles_per_month": null,
    "active": true,
    "created_at": "2026-02-12T13:23:00.724000",
    "updated_at": "2026-02-12T13:23:00.724000"
  },
  {
    "supplement_name": "Quercetin and Nettles",
    "company": "Designs for Health - Emerson",
    "units_per_bottle": 90,
    "unit_type": "caps",
    "default_quantity_per_dose": 3,
    "default_frequency_per_day": 1,
    "default_dosage_display": "3 caps per day",
    "cost_per_bottle": 40.75,
    "default_instructions": "",
    "refrigerate": false,
    "notes": "",
    "bottles_per_month": 1,
    "active": true,
    "created_at": "2026-02-12T13:23:00.724000",
    "updated_at": "2026-02-12T13:23:00.724000"
  },
  {
    "supplement_name": "R.E.M. Maintenance",
    "company": "Metabolic Maintenance - Emerson",
    "units_per_bottle": 60,
    "unit_type": "serving",
    "default_quantity_per_dose": 1,
    "default_frequency_per_day": 1,
    "default_dosage_display": "1 scoop",
    "cost_per_bottle": 56.0,
    "default_instructions": "",
    "refrigerate": false,
    "notes": "1 bottle is a 2 month supply",
    "bottles_per_month": 0.5,
    "active": true,
    "created_at": "2026-02-12T13:23:00.724000",
    "updated_at": "2026-02-12T13:23:00.724000"
  },
  {
    "supplement_name": "Reacted Magnesium Powder Strawberry",
    "company": "Ortho Molecular - Emerson",
    "units_per_bottle": 30,
    "unit_type": "serving",
    "default_quantity_per_dose": 1,
    "default_frequency_per_day": 1,
    "default_dosage_display": "1 scoop",
    "cost_per_bottle": 39.4,
    "default_instructions": "",
    "refrigerate": false,
    "notes": "1 bottle is a 2 month supply. Servings per container: 30",
    "bottles_per_month": 0.5,
    "active": true,
    "created_at": "2026-02-12T13:23:00.724000",
    "updated_at": "2026-02-12T13:23:00.724000"
  },
  {
    "supplement_name": "Renal Plus",
    "company": "Biotics",
    "units_per_bottle": 180,
    "unit_type": "caps",
    "default_quantity_per_dose": 2,
    "default_frequency_per_day": 3,
    "default_dosage_display": "2 caps 3x/day",
    "cost_per_bottle": 31.9,
    "default_instructions": "",
    "refrigerate": false,
    "notes": "For Kidneys",
    "bottles_per_month": 1,
    "active": true,
    "created_at": "2026-02-12T13:23:00.724000",
    "updated_at": "2026-02-12T13:23:00.724000"
  },
  {
    "supplement_name": "Repairvite Original K60",
    "company": "Apex",
    "units_per_bottle": 30,
    "unit_type": "serving",
    "default_quantity_per_dose": 1,
    "default_frequency_per_day": 1,
    "default_dosage_display": "1 scoop",
    "cost_per_bottle": 53.98,
    "default_instructions": "",
    "refrigerate": false,
    "notes": "",
    "bottles_per_month": 1,
    "active": true,
    "created_at": "2026-02-12T13:23:00.724000",
    "updated_at": "2026-02-12T13:23:00.724000"
  },
  {
    "supplement_name": "Seed",
    "company": "Emerson",
    "units_per_bottle": 60,
    "unit_type": "caps",
    "default_quantity_per_dose": 1,
    "default_frequency_per_day": 1,
    "default_dosage_display": "1 pill per day",
    "cost_per_bottle": 60.0,
    "default_instructions": "",
    "refrigerate": false,
    "notes": "Probiotic",
    "bottles_per_month": 1,
    "active": true,
    "created_at": "2026-02-12T13:23:00.724000",
    "updated_at": "2026-02-12T13:23:00.724000"
  },
  {
    "supplement_name": "Therbiotic",
    "company": "Klaire Labs - Emerson",
    "units_per_bottle": 60,
    "unit_type": "caps",
    "default_quantity_per_dose": 1,
    "default_frequency_per_day": 1,
    "default_dosage_display": "1 per day",
    "cost_per_bottle": 52.99,
    "default_instructions": "",
    "refrigerate": false,
    "notes": "Probiotic. 1 bottle is a 2 month supply",
    "bottles_per_month": 0.5,
    "active": true,
    "created_at": "2026-02-12T13:23:00.724000",
    "updated_at": "2026-02-12T13:23:00.724000"
  },
  {
    "supplement_name": "Thyro-CNV",
    "company": "Apex",
    "units_per_bottle": 90,
    "unit_type": "caps",
    "default_quantity_per_dose": 2,
    "default_frequency_per_day": 3,
    "default_dosage_display": "2 caps/ 3x per day",
    "cost_per_bottle": 42.98,
    "default_instructions": "",
    "refrigerate": false,
    "notes": "",
    "bottles_per_month": 2,
    "active": true,
    "created_at": "2026-02-12T13:23:00.724000",
    "updated_at": "2026-02-12T13:23:00.724000"
  },
  {
    "supplement_name": "Ultra Binder",
    "company": "Quicksilver",
    "units_per_bottle": 120,
    "unit_type": "caps",
    "default_quantity_per_dose": null,
    "default_frequency_per_day": null,
    "default_dosage_display": "",
    "cost_per_bottle": 79.99,
    "default_instructions": "",
    "refrigerate": false,
    "notes": "",
    "bottles_per_month": null,
    "active": true,
    "created_at": "2026-02-12T13:23:00.724000",
    "updated_at": "2026-02-12T13:23:00.724000"
  },
  {
    "supplement_name": "Ultra Binder - Powder",
    "company": "Quicksilver",
    "units_per_bottle": 120,
    "unit_type": "g",
    "default_quantity_per_dose": null,
    "default_frequency_per_day": null,
    "default_dosage_display": "",
    "cost_per_bottle": 84.99,
    "default_instructions": "",
    "refrigerate": false,
    "notes": "Each 4 grams delivers 2g proprietary blend. 1 tsp serving. 30 servings per bottle",
    "bottles_per_month": 1,
    "active": true,
    "created_at": "2026-02-12T13:23:00.724000",
    "updated_at": "2026-02-12T13:23:00.724000"
  },
  {
    "supplement_name": "Ultra Binder Sensitive - Powder",
    "company": "Quicksilver",
    "units_per_bottle": 121,
    "unit_type": "g",
    "default_quantity_per_dose": null,
    "default_frequency_per_day": null,
    "default_dosage_display": "",
    "cost_per_bottle": 68.99,
    "default_instructions": "",
    "refrigerate": false,
    "notes": "Low Sulfur version. Each 4g delivers 2g blend. 1 tsp serving. 30 4g servings",
    "bottles_per_month": 1,
    "active": true,
    "created_at": "2026-02-12T13:23:00.724000",
    "updated_at": "2026-02-12T13:23:00.724000"
  },
  {
    "supplement_name": "VIRADCHEM Binder",
    "company": "Cellcore",
    "units_per_bottle": 120,
    "unit_type": "caps",
    "default_quantity_per_dose": 2,
    "default_frequency_per_day": 2,
    "default_dosage_display": "2 caps 2x/day",
    "cost_per_bottle": 67.95,
    "default_instructions": "",
    "refrigerate": false,
    "notes": "",
    "bottles_per_month": 1,
    "active": true,
    "created_at": "2026-02-12T13:23:00.724000",
    "updated_at": "2026-02-12T13:23:00.724000"
  },
  {
    "supplement_name": "Vitamin D3 10,000 + K",
    "company": "Metagenics - Emerson",
    "units_per_bottle": 60,
    "unit_type": "caps",
    "default_quantity_per_dose": 1,
    "default_frequency_per_day": 1,
    "default_dosage_display": "1 cap per day",
    "cost_per_bottle": 32.5,
    "default_instructions": "",
    "refrigerate": false,
    "notes": "D3K2 capsules. 1 bottle is a 2 month supply",
    "bottles_per_month": 0.5,
    "active": true,
    "created_at": "2026-02-12T13:23:00.724000",
    "updated_at": "2026-02-12T13:23:00.724000"
  },
  {
    "supplement_name": "BC-ATP",
    "company": "Cellcore",
    "units_per_bottle": 60,
    "unit_type": "caps",
    "default_quantity_per_dose": 1,
    "default_frequency_per_day": 2,
    "default_dosage_display": "1 cap 2x/day",
    "cost_per_bottle": 0.0,
    "default_instructions": "With food",
    "refrigerate": false,
    "notes": "Added from Detox 2 Step 2 template. Price TBD.",
    "bottles_per_month": null,
    "active": true,
    "created_at": "2026-02-12T16:14:25.406000",
    "updated_at": "2026-02-12T16:14:25.406000"
  }
]